sync_list/__init__.py
sync_list/_sync_list_.py
sync_list-1.2.0.dist-info/METADATA
sync_list-1.2.0.dist-info/WHEEL
sync_list-1.2.0.dist-info/RECORD
