Metadata-Version: 2.1
Name: sync-list
Version: 1.2.0
Summary: SyncList - список Python с автоматической синхронизацией данных с файлом JSON.
Author: Azreil-OFD
Author-email: fantom2413@gmail.com
Requires-Python: >=3.10,<4.0
Classifier: Programming Language :: Python :: 3
Classifier: Programming Language :: Python :: 3.10
Classifier: Programming Language :: Python :: 3.11
Requires-Dist: pytest (>=7.3.1,<8.0.0)
